punters_client/__init__.py
punters_client/html_utils.py
punters_client/scraper.py
punters_client-1.0.0b8.dist-info/DESCRIPTION.rst
punters_client-1.0.0b8.dist-info/METADATA
punters_client-1.0.0b8.dist-info/RECORD
punters_client-1.0.0b8.dist-info/WHEEL
punters_client-1.0.0b8.dist-info/entry_points.txt
punters_client-1.0.0b8.dist-info/metadata.json
punters_client-1.0.0b8.dist-info/top_level.txt
