Metadata-Version: 2.0
Name: punters-client
Version: 1.0.0b8
Summary: Python client library for www.punters.com.au
Home-page: https://github.com/justjasongreen/punters_client
Author: Jason Green
Author-email: justjasongreen@gmail.com
License: MIT
Keywords: client library punters
Platform: UNKNOWN
Classifier: Development Status :: 4 - Beta
Classifier: Intended Audience :: Developers
Classifier: License :: OSI Approved :: MIT License
Classifier: Natural Language :: English
Classifier: Operating System :: OS Independent
Classifier: Programming Language :: Python :: 2.7
Classifier: Programming Language :: Python :: 3.5
Classifier: Topic :: Software Development :: Libraries :: Python Modules
Requires-Dist: cssselect
Requires-Dist: pytz
Requires-Dist: tzlocal
Provides-Extra: dev
Requires-Dist: bumpversion; extra == 'dev'
Requires-Dist: check-manifest; extra == 'dev'
Provides-Extra: test
Requires-Dist: tox; extra == 'test'
